<?xml version="1.0" encoding="UTF-8"?>
<objects serializationModel="Studio.02.02.00">
	<object class="AudioFile" id="{589ddc81-d353-431f-9fcd-2a73c0c5eb14}">
		<property name="assetPath">
			<value>Music/By Brian/Froguelike -Level 1.ogg</value>
		</property>
		<property name="isStreaming">
			<value>true</value>
		</property>
		<property name="frequencyInKHz">
			<value>48</value>
		</property>
		<property name="channelCount">
			<value>2</value>
		</property>
		<property name="length">
			<value>52.965520833333336</value>
		</property>
		<relationship name="masterAssetFolder">
			<destination>{75eee87a-c510-4973-8b6f-7e6e04fb4e64}</destination>
		</relationship>
	</object>
</objects>
