<?xml version="1.0" encoding="UTF-8"?>
<objects serializationModel="Studio.02.02.00">
	<object class="AudioFile" id="{500d2377-ea22-4131-b0ef-1e9d542a3212}">
		<property name="assetPath">
			<value>FIX THIS Stinger 09 - 3 to 2.wav</value>
		</property>
		<property name="frequencyInKHz">
			<value>48</value>
		</property>
		<property name="channelCount">
			<value>2</value>
		</property>
		<property name="length">
			<value>3.3103541666666665</value>
		</property>
		<relationship name="masterAssetFolder">
			<destination>{d02df48e-3f0b-4cca-a7f0-a6ef1737d79c}</destination>
		</relationship>
	</object>
</objects>
